PKBReportBuilder/__init__.py
PKBReportBuilder/configs/build_code.json
PKBReportBuilder/configs/logging.yaml
PKBReportBuilder/models/__init__.py
PKBReportBuilder/models/export_models/__init__.py
PKBReportBuilder/models/export_models/export_document.py
PKBReportBuilder/models/export_models/export_document_elements.py
PKBReportBuilder/models/export_models/export_document_report_model.py
PKBReportBuilder/models/export_models/export_styles.py
PKBReportBuilder/models/export_models/__pycache__/export_document.cpython-36.pyc
PKBReportBuilder/models/export_models/__pycache__/export_document_elements.cpython-36.pyc
PKBReportBuilder/models/export_models/__pycache__/export_document_report_model.cpython-36.pyc
PKBReportBuilder/models/export_models/__pycache__/export_styles.cpython-36.pyc
PKBReportBuilder/models/processing_tables/processing_table_models.py
PKBReportBuilder/models/processing_tables/__pycache__/processing_table_models.cpython-36.pyc
PKBReportBuilder/models/root_models/root_model.py
PKBReportBuilder/models/root_models/__pycache__/root_model.cpython-36.pyc
PKBReportBuilder/models/settings/__init__.py
PKBReportBuilder/models/settings/config.py
PKBReportBuilder/models/settings/__pycache__/config.cpython-36.pyc
PKBReportBuilder/models/tree_models/xml_navigator.py
PKBReportBuilder/models/tree_models/__pycache__/xml_navigator.cpython-36.pyc
PKBReportBuilder/modules/__init__.py
PKBReportBuilder/modules/document_converters/document_converter.py
PKBReportBuilder/modules/document_converters/__pycache__/document_converter.cpython-36.pyc
PKBReportBuilder/modules/group_data_modules/group_table_data.py
PKBReportBuilder/modules/group_data_modules/__pycache__/group_table_data.cpython-36.pyc
PKBReportBuilder/modules/io_modues/io_module.py
PKBReportBuilder/modules/io_modues/__pycache__/io_module.cpython-36.pyc
PKBReportBuilder/modules/logging/__init__.py
PKBReportBuilder/modules/logging/logging.py
pkb_report_builder-0.0.19.dist-info/DESCRIPTION.rst
pkb_report_builder-0.0.19.dist-info/METADATA
pkb_report_builder-0.0.19.dist-info/RECORD
pkb_report_builder-0.0.19.dist-info/WHEEL
pkb_report_builder-0.0.19.dist-info/metadata.json
pkb_report_builder-0.0.19.dist-info/top_level.txt
