Metadata-Version: 2.0
Name: pkb-report-builder
Version: 0.0.19
Summary: PKBReportBuilder - smaller library for extract data from PKB XML-models
Home-page: https://github.com/vyadzmak/PKBReportBuilder
Author: Alex Hvedkovich
Author-email: a.hvedkovich@netvix.by
License: UNKNOWN
Keywords: pkbreportnbuilder setuptools development
Platform: UNKNOWN
Classifier: Development Status :: 3 - Alpha
Classifier: Programming Language :: Python :: 3.7
Requires-Dist: coloredlogs
Requires-Dist: click
